first_env_test/__init__.py
first_env_test-0.1.dist-info/METADATA
first_env_test-0.1.dist-info/WHEEL
first_env_test-0.1.dist-info/top_level.txt
first_env_test-0.1.dist-info/RECORD
