Metadata-Version: 2.1
Name: first-env-test
Version: 0.1
Summary: A package that prints environment variables during installation
Author: Your Name
Author-email: your_email@example.com
Classifier: Programming Language :: Python :: 3
Classifier: License :: OSI Approved :: MIT License
Classifier: Operating System :: OS Independent
Requires-Python: >=3.6
